<?xml version="1.0"?>
<XnaContent>
  <Asset Type="XMLContent.Level">
    <levelNum>1</levelNum>
    <seamstress>
      <position>1.5 -6.5</position>
    </seamstress>
    <ground>
      <Item>
        <position>33 -30</position>
        <dimensions>1 1</dimensions>
      </Item>
      <Item>
        <position>0 -1</position>
        <dimensions>1 1</dimensions>
      </Item>
      <Item>
        <position>0 -2</position>
        <dimensions>1 1</dimensions>
      </Item>
      <Item>
        <position>0 -3</position>
        <dimensions>1 1</dimensions>
      </Item>
      <Item>
        <position>0 -4</position>
        <dimensions>1 1</dimensions>
      </Item>
      <Item>
        <position>0 -5</position>
        <dimensions>1 1</dimensions>
      </Item>
      <Item>
        <position>0 -6</position>
        <dimensions>1 1</dimensions>
      </Item>
      <Item>
        <position>1 -1</position>
        <dimensions>1 1</dimensions>
      </Item>
      <Item>
        <position>1 -2</position>
        <dimensions>1 1</dimensions>
      </Item>
      <Item>
        <position>1 -3</position>
        <dimensions>1 1</dimensions>
      </Item>
      <Item>
        <position>1 -4</position>
        <dimensions>1 1</dimensions>
      </Item>
      <Item>
        <position>1 -5</position>
        <dimensions>1 1</dimensions>
      </Item>
      <Item>
        <position>1 -6</position>
        <dimensions>1 1</dimensions>
      </Item>
      <Item>
        <position>2 -1</position>
        <dimensions>1 1</dimensions>
      </Item>
      <Item>
        <position>2 -2</position>
        <dimensions>1 1</dimensions>
      </Item>
      <Item>
        <position>2 -3</position>
        <dimensions>1 1</dimensions>
      </Item>
      <Item>
        <position>2 -4</position>
        <dimensions>1 1</dimensions>
      </Item>
      <Item>
        <position>2 -5</position>
        <dimensions>1 1</dimensions>
      </Item>
      <Item>
        <position>2 -6</position>
        <dimensions>1 1</dimensions>
      </Item>
      <Item>
        <position>3 -1</position>
        <dimensions>1 1</dimensions>
      </Item>
      <Item>
        <position>3 -2</position>
        <dimensions>1 1</dimensions>
      </Item>
      <Item>
        <position>3 -3</position>
        <dimensions>1 1</dimensions>
      </Item>
      <Item>
        <position>3 -4</position>
        <dimensions>1 1</dimensions>
      </Item>
      <Item>
        <position>3 -5</position>
        <dimensions>1 1</dimensions>
      </Item>
      <Item>
        <position>3 -6</position>
        <dimensions>1 1</dimensions>
      </Item>
      <Item>
        <position>4 -1</position>
        <dimensions>1 1</dimensions>
      </Item>
      <Item>
        <position>4 -2</position>
        <dimensions>1 1</dimensions>
      </Item>
      <Item>
        <position>4 -3</position>
        <dimensions>1 1</dimensions>
      </Item>
      <Item>
        <position>4 -4</position>
        <dimensions>1 1</dimensions>
      </Item>
      <Item>
        <position>4 -5</position>
        <dimensions>1 1</dimensions>
      </Item>
      <Item>
        <position>4 -6</position>
        <dimensions>1 1</dimensions>
      </Item>
      <Item>
        <position>5 -1</position>
        <dimensions>1 1</dimensions>
      </Item>
      <Item>
        <position>5 -2</position>
        <dimensions>1 1</dimensions>
      </Item>
      <Item>
        <position>5 -3</position>
        <dimensions>1 1</dimensions>
      </Item>
      <Item>
        <position>5 -4</position>
        <dimensions>1 1</dimensions>
      </Item>
      <Item>
        <position>5 -5</position>
        <dimensions>1 1</dimensions>
      </Item>
      <Item>
        <position>5 -6</position>
        <dimensions>1 1</dimensions>
      </Item>
      <Item>
        <position>6 -1</position>
        <dimensions>1 1</dimensions>
      </Item>
      <Item>
        <position>6 -2</position>
        <dimensions>1 1</dimensions>
      </Item>
      <Item>
        <position>6 -3</position>
        <dimensions>1 1</dimensions>
      </Item>
      <Item>
        <position>6 -4</position>
        <dimensions>1 1</dimensions>
      </Item>
      <Item>
        <position>6 -5</position>
        <dimensions>1 1</dimensions>
      </Item>
      <Item>
        <position>6 -6</position>
        <dimensions>1 1</dimensions>
      </Item>
      <Item>
        <position>7 -1</position>
        <dimensions>1 1</dimensions>
      </Item>
      <Item>
        <position>7 -2</position>
        <dimensions>1 1</dimensions>
      </Item>
      <Item>
        <position>7 -3</position>
        <dimensions>1 1</dimensions>
      </Item>
      <Item>
        <position>7 -4</position>
        <dimensions>1 1</dimensions>
      </Item>
      <Item>
        <position>7 -5</position>
        <dimensions>1 1</dimensions>
      </Item>
      <Item>
        <position>7 -6</position>
        <dimensions>1 1</dimensions>
      </Item>
      <Item>
        <position>8 -1</position>
        <dimensions>1 1</dimensions>
      </Item>
      <Item>
        <position>8 -2</position>
        <dimensions>1 1</dimensions>
      </Item>
      <Item>
        <position>8 -3</position>
        <dimensions>1 1</dimensions>
      </Item>
      <Item>
        <position>8 -4</position>
        <dimensions>1 1</dimensions>
      </Item>
      <Item>
        <position>8 -5</position>
        <dimensions>1 1</dimensions>
      </Item>
      <Item>
        <position>9 -1</position>
        <dimensions>1 1</dimensions>
      </Item>
      <Item>
        <position>9 -2</position>
        <dimensions>1 1</dimensions>
      </Item>
      <Item>
        <position>9 -3</position>
        <dimensions>1 1</dimensions>
      </Item>
      <Item>
        <position>9 -4</position>
        <dimensions>1 1</dimensions>
      </Item>
      <Item>
        <position>10 -1</position>
        <dimensions>1 1</dimensions>
      </Item>
      <Item>
        <position>10 -2</position>
        <dimensions>1 1</dimensions>
      </Item>
      <Item>
        <position>10 -3</position>
        <dimensions>1 1</dimensions>
      </Item>
      <Item>
        <position>11 -1</position>
        <dimensions>1 1</dimensions>
      </Item>
      <Item>
        <position>12 -1</position>
        <dimensions>1 1</dimensions>
      </Item>
      <Item>
        <position>13 -1</position>
        <dimensions>1 1</dimensions>
      </Item>
      <Item>
        <position>14 -1</position>
        <dimensions>1 1</dimensions>
      </Item>
      <Item>
        <position>14 -10</position>
        <dimensions>1 1</dimensions>
      </Item>
      <Item>
        <position>14 -11</position>
        <dimensions>1 1</dimensions>
      </Item>
      <Item>
        <position>15 -1</position>
        <dimensions>1 1</dimensions>
      </Item>
      <Item>
        <position>15 -10</position>
        <dimensions>1 1</dimensions>
      </Item>
      <Item>
        <position>16 -1</position>
        <dimensions>1 1</dimensions>
      </Item>
      <Item>
        <position>17 -1</position>
        <dimensions>1 1</dimensions>
      </Item>
      <Item>
        <position>18 -1</position>
        <dimensions>1 1</dimensions>
      </Item>
      <Item>
        <position>19 -1</position>
        <dimensions>1 1</dimensions>
      </Item>
      <Item>
        <position>20 -1</position>
        <dimensions>1 1</dimensions>
      </Item>
      <Item>
        <position>21 -1</position>
        <dimensions>1 1</dimensions>
      </Item>
      <Item>
        <position>22 -1</position>
        <dimensions>1 1</dimensions>
      </Item>
      <Item>
        <position>22 -2</position>
        <dimensions>1 1</dimensions>
      </Item>
      <Item>
        <position>22 -3</position>
        <dimensions>1 1</dimensions>
      </Item>
      <Item>
        <position>22 -7</position>
        <dimensions>1 1</dimensions>
      </Item>
      <Item>
        <position>22 -8</position>
        <dimensions>1 1</dimensions>
      </Item>
      <Item>
        <position>22 -9</position>
        <dimensions>1 1</dimensions>
      </Item>
      <Item>
        <position>23 -1</position>
        <dimensions>1 1</dimensions>
      </Item>
      <Item>
        <position>23 -2</position>
        <dimensions>1 1</dimensions>
      </Item>
      <Item>
        <position>23 -3</position>
        <dimensions>1 1</dimensions>
      </Item>
      <Item>
        <position>23 -7</position>
        <dimensions>1 1</dimensions>
      </Item>
      <Item>
        <position>23 -8</position>
        <dimensions>1 1</dimensions>
      </Item>
      <Item>
        <position>23 -9</position>
        <dimensions>1 1</dimensions>
      </Item>
      <Item>
        <position>24 -1</position>
        <dimensions>1 1</dimensions>
      </Item>
      <Item>
        <position>24 -2</position>
        <dimensions>1 1</dimensions>
      </Item>
      <Item>
        <position>24 -3</position>
        <dimensions>1 1</dimensions>
      </Item>
      <Item>
        <position>24 -7</position>
        <dimensions>1 1</dimensions>
      </Item>
      <Item>
        <position>24 -8</position>
        <dimensions>1 1</dimensions>
      </Item>
      <Item>
        <position>24 -9</position>
        <dimensions>1 1</dimensions>
      </Item>
      <Item>
        <position>24 -13</position>
        <dimensions>1 1</dimensions>
      </Item>
      <Item>
        <position>25 -1</position>
        <dimensions>1 1</dimensions>
      </Item>
      <Item>
        <position>25 -2</position>
        <dimensions>1 1</dimensions>
      </Item>
      <Item>
        <position>25 -3</position>
        <dimensions>1 1</dimensions>
      </Item>
      <Item>
        <position>25 -7</position>
        <dimensions>1 1</dimensions>
      </Item>
      <Item>
        <position>25 -8</position>
        <dimensions>1 1</dimensions>
      </Item>
      <Item>
        <position>25 -9</position>
        <dimensions>1 1</dimensions>
      </Item>
      <Item>
        <position>26 -1</position>
        <dimensions>1 1</dimensions>
      </Item>
      <Item>
        <position>26 -2</position>
        <dimensions>1 1</dimensions>
      </Item>
      <Item>
        <position>26 -3</position>
        <dimensions>1 1</dimensions>
      </Item>
      <Item>
        <position>26 -7</position>
        <dimensions>1 1</dimensions>
      </Item>
      <Item>
        <position>26 -8</position>
        <dimensions>1 1</dimensions>
      </Item>
      <Item>
        <position>26 -9</position>
        <dimensions>1 1</dimensions>
      </Item>
      <Item>
        <position>27 -1</position>
        <dimensions>1 1</dimensions>
      </Item>
      <Item>
        <position>27 -2</position>
        <dimensions>1 1</dimensions>
      </Item>
      <Item>
        <position>27 -3</position>
        <dimensions>1 1</dimensions>
      </Item>
      <Item>
        <position>27 -7</position>
        <dimensions>1 1</dimensions>
      </Item>
      <Item>
        <position>27 -8</position>
        <dimensions>1 1</dimensions>
      </Item>
      <Item>
        <position>27 -9</position>
        <dimensions>1 1</dimensions>
      </Item>
      <Item>
        <position>28 -1</position>
        <dimensions>1 1</dimensions>
      </Item>
      <Item>
        <position>28 -2</position>
        <dimensions>1 1</dimensions>
      </Item>
      <Item>
        <position>28 -3</position>
        <dimensions>1 1</dimensions>
      </Item>
      <Item>
        <position>28 -7</position>
        <dimensions>1 1</dimensions>
      </Item>
      <Item>
        <position>29 -1</position>
        <dimensions>1 1</dimensions>
      </Item>
      <Item>
        <position>29 -2</position>
        <dimensions>1 1</dimensions>
      </Item>
      <Item>
        <position>29 -3</position>
        <dimensions>1 1</dimensions>
      </Item>
      <Item>
        <position>30 -1</position>
        <dimensions>1 1</dimensions>
      </Item>
      <Item>
        <position>30 -2</position>
        <dimensions>1 1</dimensions>
      </Item>
      <Item>
        <position>30 -3</position>
        <dimensions>1 1</dimensions>
      </Item>
      <Item>
        <position>31 -1</position>
        <dimensions>1 1</dimensions>
      </Item>
      <Item>
        <position>31 -2</position>
        <dimensions>1 1</dimensions>
      </Item>
      <Item>
        <position>31 -3</position>
        <dimensions>1 1</dimensions>
      </Item>
      <Item>
        <position>31 -4</position>
        <dimensions>1 1</dimensions>
      </Item>
      <Item>
        <position>31 -5</position>
        <dimensions>1 1</dimensions>
      </Item>
      <Item>
        <position>32 -1</position>
        <dimensions>1 1</dimensions>
      </Item>
      <Item>
        <position>32 -2</position>
        <dimensions>1 1</dimensions>
      </Item>
      <Item>
        <position>32 -3</position>
        <dimensions>1 1</dimensions>
      </Item>
      <Item>
        <position>32 -4</position>
        <dimensions>1 1</dimensions>
      </Item>
      <Item>
        <position>32 -5</position>
        <dimensions>1 1</dimensions>
      </Item>
      <Item>
        <position>32 -6</position>
        <dimensions>1 1</dimensions>
      </Item>
      <Item>
        <position>32 -7</position>
        <dimensions>1 1</dimensions>
      </Item>
      <Item>
        <position>32 -8</position>
        <dimensions>1 1</dimensions>
      </Item>
      <Item>
        <position>32 -9</position>
        <dimensions>1 1</dimensions>
      </Item>
      <Item>
        <position>32 -10</position>
        <dimensions>1 1</dimensions>
      </Item>
      <Item>
        <position>32 -11</position>
        <dimensions>1 1</dimensions>
      </Item>
      <Item>
        <position>32 -12</position>
        <dimensions>1 1</dimensions>
      </Item>
      <Item>
        <position>32 -13</position>
        <dimensions>1 1</dimensions>
      </Item>
      <Item>
        <position>32 -14</position>
        <dimensions>1 1</dimensions>
      </Item>
      <Item>
        <position>32 -15</position>
        <dimensions>1 1</dimensions>
      </Item>
      <Item>
        <position>33 -1</position>
        <dimensions>1 1</dimensions>
      </Item>
      <Item>
        <position>33 -2</position>
        <dimensions>1 1</dimensions>
      </Item>
      <Item>
        <position>33 -3</position>
        <dimensions>1 1</dimensions>
      </Item>
      <Item>
        <position>33 -4</position>
        <dimensions>1 1</dimensions>
      </Item>
      <Item>
        <position>33 -5</position>
        <dimensions>1 1</dimensions>
      </Item>
      <Item>
        <position>33 -6</position>
        <dimensions>1 1</dimensions>
      </Item>
      <Item>
        <position>33 -7</position>
        <dimensions>1 1</dimensions>
      </Item>
      <Item>
        <position>33 -8</position>
        <dimensions>1 1</dimensions>
      </Item>
      <Item>
        <position>33 -9</position>
        <dimensions>1 1</dimensions>
      </Item>
      <Item>
        <position>33 -10</position>
        <dimensions>1 1</dimensions>
      </Item>
      <Item>
        <position>33 -11</position>
        <dimensions>1 1</dimensions>
      </Item>
      <Item>
        <position>33 -12</position>
        <dimensions>1 1</dimensions>
      </Item>
      <Item>
        <position>33 -13</position>
        <dimensions>1 1</dimensions>
      </Item>
      <Item>
        <position>33 -14</position>
        <dimensions>1 1</dimensions>
      </Item>
      <Item>
        <position>33 -15</position>
        <dimensions>1 1</dimensions>
      </Item>
    </ground>
    <miasma>
      <Item>
        <position>11 -2</position>
        <dimensions>1 1</dimensions>
      </Item>
      <Item>
        <position>11 -3</position>
        <dimensions>1 1</dimensions>
      </Item>
      <Item>
        <position>12 -2</position>
        <dimensions>1 1</dimensions>
      </Item>
      <Item>
        <position>12 -3</position>
        <dimensions>1 1</dimensions>
      </Item>
      <Item>
        <position>13 -2</position>
        <dimensions>1 1</dimensions>
      </Item>
      <Item>
        <position>13 -3</position>
        <dimensions>1 1</dimensions>
      </Item>
      <Item>
        <position>14 -2</position>
        <dimensions>1 1</dimensions>
      </Item>
      <Item>
        <position>14 -3</position>
        <dimensions>1 1</dimensions>
      </Item>
      <Item>
        <position>15 -2</position>
        <dimensions>1 1</dimensions>
      </Item>
      <Item>
        <position>15 -3</position>
        <dimensions>1 1</dimensions>
      </Item>
      <Item>
        <position>16 -2</position>
        <dimensions>1 1</dimensions>
      </Item>
      <Item>
        <position>16 -3</position>
        <dimensions>1 1</dimensions>
      </Item>
      <Item>
        <position>17 -2</position>
        <dimensions>1 1</dimensions>
      </Item>
      <Item>
        <position>17 -3</position>
        <dimensions>1 1</dimensions>
      </Item>
      <Item>
        <position>18 -2</position>
        <dimensions>1 1</dimensions>
      </Item>
      <Item>
        <position>18 -3</position>
        <dimensions>1 1</dimensions>
      </Item>
      <Item>
        <position>19 -2</position>
        <dimensions>1 1</dimensions>
      </Item>
      <Item>
        <position>19 -3</position>
        <dimensions>1 1</dimensions>
      </Item>
      <Item>
        <position>20 -2</position>
        <dimensions>1 1</dimensions>
      </Item>
      <Item>
        <position>20 -3</position>
        <dimensions>1 1</dimensions>
      </Item>
      <Item>
        <position>21 -2</position>
        <dimensions>1 1</dimensions>
      </Item>
      <Item>
        <position>21 -3</position>
        <dimensions>1 1</dimensions>
      </Item>
    </miasma>
    <gameGrid>38 -16</gameGrid>
    <ribbons>
      <Item>
        <path>3 -6
32 -6
32 -12
16 -12
</path>
        <start>1</start>
        <end>4</end>
        <loop>false</loop>
        <color>0</color>
      </Item>
    </ribbons>
    <cameras />
    <ribbonBoxes />
    <shooters />
    <needles />
    <hooks>
      <Item>
        <ribbonID>0</ribbonID>
        <ribbonPosition>2</ribbonPosition>
        <dimensions>1 2</dimensions>
        <flipped>false</flipped>
      </Item>
    </hooks>
    <telescopingBlocks />
    <flipbars />
    <rotatingPlatforms />
    <saveRocks>
      <Item>
        <position>
          33 -15.5
        </position>
        <endFlag>
          1
        </endFlag>
      </Item>
    </saveRocks>
    <decorations />
    <collectables>
        <Item>
          <position>15 -13</position>
          <id>0</id>
        </Item>
        <Item>
          <position>26 -21</position>
          <id>1</id>
        </Item>
        <Item>
          <position>31 -10</position>
          <id>2</id>
        </Item>
    </collectables>
    <gems />
  </Asset>
</XnaContent>